aracnid_config/__init__.py
aracnid_config/config.py
aracnid_config/logging_config.json
aracnid_config-1.1.0.dist-info/LICENSE
aracnid_config-1.1.0.dist-info/WHEEL
aracnid_config-1.1.0.dist-info/METADATA
aracnid_config-1.1.0.dist-info/RECORD
