Metadata-Version: 2.1
Name: aracnid-config
Version: 1.1.0
Summary: Custom configuration class that uses MongoDB as the backend database
Home-page: https://github.com/aracnid/aracnid-config
License: MIT
Keywords: python,mongodb,config
Author: Jason Romano
Author-email: aracnid@gmail.com
Requires-Python: >=3.10,<4.0
Classifier: License :: OSI Approved :: MIT License
Classifier: Programming Language :: Python :: 3
Classifier: Programming Language :: Python :: 3.10
Classifier: Programming Language :: Python :: 3.11
Requires-Dist: aracnid-logger (>=1.0,<2.0)
Requires-Dist: i-mongodb (>=2.0,<3.0)
Project-URL: Repository, https://github.com/aracnid/aracnid-config
